{
  "main": {
    "id": "4bc723f204e9df3e",
    "type": "split",
    "children": [
      {
        "id": "9d4f08b3c6a9b326",
        "type": "tabs",
        "children": [
          {
            "id": "56ae8f7a46377c21",
            "type": "leaf",
            "state": {
              "type": "markdown",
              "state": {
                "file": "wiki/Tools/Typst.md",
                "mode": "source",
                "source": false
              }
            }
          }
        ]
      }
    ],
    "direction": "vertical"
  },
  "left": {
    "id": "4b25d3fc273cd87a",
    "type": "split",
    "children": [
      {
        "id": "bdc1cd69102225d8",
        "type": "tabs",
        "children": [
          {
            "id": "aabcd512d6b73859",
            "type": "leaf",
            "state": {
              "type": "file-explorer",
              "state": {
                "sortOrder": "alphabetical"
              }
            }
          },
          {
            "id": "c11b52c94da51734",
            "type": "leaf",
            "state": {
              "type": "search",
              "state": {
                "query": "",
                "matchingCase": false,
                "explainSearch": false,
                "collapseAll": false,
                "extraContext": false,
                "sortOrder": "alphabetical"
              }
            }
          },
          {
            "id": "48d607a02dc0bea2",
            "type": "leaf",
            "state": {
              "type": "bookmarks",
              "state": {}
            }
          }
        ]
      }
    ],
    "direction": "horizontal",
    "width": 300
  },
  "right": {
    "id": "0340334a632fb3d4",
    "type": "split",
    "children": [
      {
        "id": "2bca5f2774c8b84a",
        "type": "tabs",
        "children": [
          {
            "id": "4b70b73dc0e94a04",
            "type": "leaf",
            "state": {
              "type": "backlink",
              "state": {
                "file": "wiki/Tools/Typst.md",
                "collapseAll": false,
                "extraContext": false,
                "sortOrder": "alphabetical",
                "showSearch": false,
                "searchQuery": "",
                "backlinkCollapsed": false,
                "unlinkedCollapsed": true
              }
            }
          },
          {
            "id": "c68e1c8c0a27f904",
            "type": "leaf",
            "state": {
              "type": "outgoing-link",
              "state": {
                "file": "wiki/Tools/Typst.md",
                "linksCollapsed": false,
                "unlinkedCollapsed": true
              }
            }
          },
          {
            "id": "2b8fe9835bab4635",
            "type": "leaf",
            "state": {
              "type": "tag",
              "state": {
                "sortOrder": "frequency",
                "useHierarchy": true
              }
            }
          },
          {
            "id": "191c92f5fd06cc12",
            "type": "leaf",
            "state": {
              "type": "outline",
              "state": {
                "file": "wiki/Tools/Typst.md"
              }
            }
          }
        ],
        "currentTab": 2
      }
    ],
    "direction": "horizontal",
    "width": 300,
    "collapsed": true
  },
  "left-ribbon": {
    "hiddenItems": {
      "switcher:打开快速切换": false,
      "graph:查看关系图谱": false,
      "canvas:新建白板": false,
      "daily-notes:打开/创建今天的日记": false,
      "templates:插入模板": false,
      "command-palette:打开命令面板": false
    }
  },
  "active": "56ae8f7a46377c21",
  "lastOpenFiles": [
    "wiki/Tools/Obisidian.md",
    "wiki/Tools/Typst.md",
    "mooc/hias-algorithm/lecture31_2023-10-26-elementary-graph-algorithms.pdf",
    "wiki/Algorithm/Graph.md",
    "wiki/Algorithm/Dynamic Programming.md",
    "wiki/Algorithm/Heap sort.md",
    "mooc/hias-algorithm/problem.pdf",
    "wiki/Algorithm/Asymptotic notations.md",
    "wiki/Algorithm/Amortized Analysis.md",
    "wiki/Algorithm/Breadth-first Search.md",
    "wiki/Algorithm/Depth-first Search.md",
    "mooc/hias-algorithm/期末考试复习题.pdf",
    "mooc/hias-algorithm/~$末考试复习题.docx",
    "mooc/hias-algorithm/期末考试复习题.docx",
    "mooc/hias-algorithm/期末考试复习题~C320D.tmp",
    "wiki/Algorithm/Recurrences.md",
    "wiki/Algorithm/Linear Programming.md",
    "mooc/hias-algorithm/lecture34_2023-11-07-Linear-Programming.pdf",
    "mooc/hias-algorithm/lecture35_2023-11-08-Linear-Programming.pdf",
    "wiki/Algorithm/All-Pairs Shortest Paths.md",
    "mooc/hias-algorithm/lecture36_2023-11-15-maximum-flow.pdf",
    "wiki/Algorithm/Single-Source  Shortest Paths.md",
    "wiki/Algorithm/Minimum  Spanning Tree.md",
    "wiki/Algorithm/Strongly Connected  Components.md",
    "wiki/Algorithm/Topological Sort.md",
    "mooc/hias-algorithm/lecture30_2023-10-25-amortized-analysis.pdf",
    "wiki/Algorithm/Hash.md",
    "wiki/Algorithm/Greedy Algorithms.md",
    "wiki/Algorithm/Red-Black Trees.md",
    "wiki/Algorithm/B Trees.md",
    "wiki/Algorithm/Binary Search Trees.md",
    "wiki/Algorithm/Comparison  Sort Algorithms.md",
    "wiki/Algorithm/Quickselect.md",
    "wiki/Algorithm/Selection sort.md",
    "wiki/Algorithm/Selection.md",
    "wiki/Algorithm/Insertion sort.md"
  ]
}